{
  "crinacle5128": {
    "hash": "b12f5042ec523c0c",
    "lastChecked": "2026-02-28T22:29:48.915Z",
    "entryCount": 448
  },
  "crinacleHP": {
    "hash": "cfd132f402921fb2",
    "lastChecked": "2026-02-28T22:29:49.175Z",
    "entryCount": 286
  },
  "crinacle": {
    "hash": "cc6f648865cf4330",
    "lastChecked": "2026-02-28T22:29:45.407Z",
    "entryCount": 1185
  },
  "vortexreviews": {
    "hash": "b4c6e518f54283b2",
    "lastChecked": "2026-02-28T22:29:45.527Z",
    "entryCount": 403
  },
  "arc": {
    "hash": "f4054e49c8451d2a",
    "lastChecked": "2026-02-28T22:29:45.541Z",
    "entryCount": 22
  },
  "nymz": {
    "hash": "7d0f4dff0346136b",
    "lastChecked": "2026-02-28T22:29:45.571Z",
    "entryCount": 126
  },
  "bakkwatan": {
    "hash": "d544e73b704fcfe0",
    "lastChecked": "2026-02-28T22:29:45.652Z",
    "entryCount": 36
  },
  "rg": {
    "hash": "c768e6676d49c5ae",
    "lastChecked": "2026-02-28T22:29:45.604Z",
    "entryCount": 146
  },
  "gadgetrytech": {
    "hash": "1922cfc11f5205e6",
    "lastChecked": "2026-02-28T22:29:45.629Z",
    "entryCount": 132
  },
  "eliseaudio": {
    "hash": "33ab6a788b0d463a",
    "lastChecked": "2026-02-28T22:29:45.737Z",
    "entryCount": 266
  },
  "precog": {
    "hash": "66e90618ed5a22ba",
    "lastChecked": "2026-02-28T22:29:45.431Z",
    "entryCount": 386
  },
  "adri-n": {
    "hash": "7e700fcbb6f5547d",
    "lastChecked": "2026-02-28T22:29:45.674Z",
    "entryCount": 68
  },
  "achoreviews": {
    "hash": "086180d2a2aa7034",
    "lastChecked": "2026-02-28T22:29:45.662Z",
    "entryCount": 185
  },
  "arn": {
    "hash": "ef0945673d9a4d03",
    "lastChecked": "2026-02-28T22:29:45.677Z",
    "entryCount": 291
  },
  "bassyalexander": {
    "hash": "15af97a705c39604",
    "lastChecked": "2026-02-28T22:29:45.863Z",
    "entryCount": 100
  },
  "awsmdanny": {
    "hash": "63c26e0fb7b5d19e",
    "lastChecked": "2026-02-28T22:29:45.721Z",
    "entryCount": 77
  },
  "bedrock": {
    "hash": "3d40a724f4db9551",
    "lastChecked": "2026-02-28T22:29:45.860Z",
    "entryCount": 117
  },
  "banzai1122": {
    "hash": "0ca43849666fa5ca",
    "lastChecked": "2026-02-28T22:29:45.806Z",
    "entryCount": 39
  },
  "bassaudio": {
    "hash": "fbc9411f916103ac",
    "lastChecked": "2026-02-28T22:29:45.817Z",
    "entryCount": 107
  },
  "paulwasabii": {
    "hash": "5718a65208abd99b",
    "lastChecked": "2026-02-28T22:29:45.612Z",
    "entryCount": 586
  },
  "atechreviews": {
    "hash": "e6363b6d8bf5a1d5",
    "lastChecked": "2026-02-28T22:29:46.049Z",
    "entryCount": 306
  },
  "theaudiostore": {
    "hash": "4a875b8b22aae9b1",
    "lastChecked": "2026-02-28T22:29:45.835Z",
    "entryCount": 226
  },
  "audioamigo": {
    "hash": "ba8b26bbd1885e91",
    "lastChecked": "2026-02-28T22:29:45.996Z",
    "entryCount": 427
  },
  "animagus": {
    "hash": "263a057fd7ccd5bb",
    "lastChecked": "2026-02-28T22:29:45.524Z",
    "entryCount": 106
  },
  "superreview": {
    "hash": "1209b535079c9d42",
    "lastChecked": "2026-02-28T22:29:45.775Z",
    "entryCount": 549
  },
  "ankramutt": {
    "hash": "9df516c98befaf0c",
    "lastChecked": "2026-02-28T22:29:45.845Z",
    "entryCount": 196
  },
  "tonedeafmonk": {
    "hash": "f317634a3584e1b5",
    "lastChecked": "2026-02-28T22:29:45.687Z",
    "entryCount": 375
  },
  "timmyv": {
    "hash": "304fababce0df539",
    "lastChecked": "2026-02-28T22:29:45.657Z",
    "entryCount": 305
  },
  "aftersound": {
    "hash": "d6b2945fe981966b",
    "lastChecked": "2026-02-28T22:29:45.617Z",
    "entryCount": 856
  },
  "aden": {
    "hash": "76d413203861caec",
    "lastChecked": "2026-02-28T22:29:45.803Z",
    "entryCount": 364
  },
  "hbb": {
    "hash": "eb4f2ff149f1fb4c",
    "lastChecked": "2026-02-28T22:29:45.543Z",
    "entryCount": 774
  },
  "den-fi": {
    "hash": "5c7cbeacdd01df17",
    "lastChecked": "2026-02-28T22:29:45.715Z",
    "entryCount": 134
  },
  "breampike": {
    "hash": "e4ebdca4f9d8b779",
    "lastChecked": "2026-02-28T22:29:46.822Z",
    "entryCount": 79
  },
  "bukanaudiophile": {
    "hash": "f98ecc92a07350fe",
    "lastChecked": "2026-02-28T22:29:46.837Z",
    "entryCount": 58
  },
  "boizoff": {
    "hash": "1707447e116d3205",
    "lastChecked": "2026-02-28T22:29:46.958Z",
    "entryCount": 219
  },
  "enemyspider": {
    "hash": "cf164f88170c1ba9",
    "lastChecked": "2026-02-28T22:29:46.908Z",
    "entryCount": 116
  },
  "ekaudio": {
    "hash": "4d34a545efb992df",
    "lastChecked": "2026-02-28T22:29:46.875Z",
    "entryCount": 67
  },
  "foxtoldmeso": {
    "hash": "460934738d6da8c4",
    "lastChecked": "2026-02-28T22:29:46.885Z",
    "entryCount": 35
  },
  "csi-zone": {
    "hash": "92d4316c67938d0c",
    "lastChecked": "2026-02-28T22:29:46.976Z",
    "entryCount": 167
  },
  "isaiahse": {
    "hash": "0e7fde57b881b19f",
    "lastChecked": "2026-02-28T22:29:46.857Z",
    "entryCount": 25
  },
  "hadoe": {
    "hash": "56615b08e0b77651",
    "lastChecked": "2026-02-28T22:29:46.906Z",
    "entryCount": 43
  },
  "jacstone": {
    "hash": "954712307a419c4a",
    "lastChecked": "2026-02-28T22:29:46.821Z",
    "entryCount": 89
  },
  "joshtbvo": {
    "hash": "288f74bfea542096",
    "lastChecked": "2026-02-28T22:29:46.851Z",
    "entryCount": 39
  },
  "eplv": {
    "hash": "3e915cedc5579497",
    "lastChecked": "2026-02-28T22:29:46.908Z",
    "entryCount": 388
  },
  "dhrme": {
    "hash": "7b6be6d572ad0010",
    "lastChecked": "2026-02-28T22:29:46.973Z",
    "entryCount": 75
  },
  "ideru": {
    "hash": "e757a6ab601bf8c3",
    "lastChecked": "2026-02-28T22:29:46.910Z",
    "entryCount": 49
  },
  "fahryst": {
    "hash": "e1888a64d2edb1e7",
    "lastChecked": "2026-02-28T22:29:46.862Z",
    "entryCount": 144
  },
  "flare": {
    "hash": "873d6827994c9b6a",
    "lastChecked": "2026-02-28T22:29:46.881Z",
    "entryCount": 119
  },
  "bryaudioreviews": {
    "hash": "4b8050e33a451645",
    "lastChecked": "2026-02-28T22:29:46.692Z",
    "entryCount": 89
  },
  "iemocean": {
    "hash": "6f7dda6ce8769d76",
    "lastChecked": "2026-02-28T22:29:47.074Z",
    "entryCount": 126
  },
  "kazi": {
    "hash": "f1305985578ed275",
    "lastChecked": "2026-02-28T22:29:46.951Z",
    "entryCount": 134
  },
  "dchpgall": {
    "hash": "f81636d4f310780c",
    "lastChecked": "2026-02-28T22:29:46.983Z",
    "entryCount": 344
  },
  "iemworld": {
    "hash": "4ebf2c7170418184",
    "lastChecked": "2026-02-28T22:29:47.061Z",
    "entryCount": 150
  },
  "hu-fi": {
    "hash": "87038add34126c50",
    "lastChecked": "2026-02-28T22:29:47.082Z",
    "entryCount": 283
  },
  "freeryder05": {
    "hash": "1cfe845cc1e783f4",
    "lastChecked": "2026-02-28T22:29:46.772Z",
    "entryCount": 54
  },
  "dl": {
    "hash": "f442870323da1e16",
    "lastChecked": "2026-02-28T22:29:46.875Z",
    "entryCount": 172
  },
  "jaytiss": {
    "hash": "d43d21e22e14f738",
    "lastChecked": "2026-02-28T22:29:47.215Z",
    "entryCount": 478
  },
  "hore": {
    "hash": "20e33338269bfd04",
    "lastChecked": "2026-02-28T22:29:46.829Z",
    "entryCount": 49
  },
  "ianfann": {
    "hash": "42cdd77988ea62dc",
    "lastChecked": "2026-02-28T22:29:46.930Z",
    "entryCount": 408
  },
  "harpo": {
    "hash": "65b8a70d37592bcb",
    "lastChecked": "2026-02-28T22:29:46.926Z",
    "entryCount": 181
  },
  "ducbloke": {
    "hash": "e2114b71d8f928b3",
    "lastChecked": "2026-02-28T22:29:47.017Z",
    "entryCount": 246
  },
  "doltonius": {
    "hash": "d1a3a7b888f80cde",
    "lastChecked": "2026-02-28T22:29:46.848Z",
    "entryCount": 32
  },
  "pw": {
    "hash": "5718a65208abd99b",
    "lastChecked": "2026-02-28T22:29:47.658Z",
    "entryCount": 586
  },
  "lestat": {
    "hash": "401148e2be046179",
    "lastChecked": "2026-02-28T22:29:47.841Z",
    "entryCount": 32
  },
  "ragnarok": {
    "hash": "9247ff78f821ccdb",
    "lastChecked": "2026-02-28T22:29:47.869Z",
    "entryCount": 29
  },
  "loomynarty": {
    "hash": "fdcd7547db35cb4b",
    "lastChecked": "2026-02-28T22:29:47.963Z",
    "entryCount": 30
  },
  "riz": {
    "hash": "77e366fe9883da85",
    "lastChecked": "2026-02-28T22:29:47.868Z",
    "entryCount": 48
  },
  "melatonin": {
    "hash": "d501cd9723eeab3f",
    "lastChecked": "2026-02-28T22:29:48.000Z",
    "entryCount": 215
  },
  "suporsalad": {
    "hash": "60cfe840fa059eb2",
    "lastChecked": "2026-02-28T22:29:47.880Z",
    "entryCount": 94
  },
  "kr0mka": {
    "hash": "8db1e7b824b1da73",
    "lastChecked": "2026-02-28T22:29:47.985Z",
    "entryCount": 83
  },
  "obodio": {
    "hash": "c3bc86bab84590f4",
    "lastChecked": "2026-02-28T22:29:47.979Z",
    "entryCount": 167
  },
  "scboy": {
    "hash": "151f73617e3f1646",
    "lastChecked": "2026-02-28T22:29:47.945Z",
    "entryCount": 46
  },
  "tanchjim": {
    "hash": "645645efc2a5775f",
    "lastChecked": "2026-02-28T22:29:47.969Z",
    "entryCount": 10
  },
  "yanyin": {
    "hash": "15d731cead6f1d8b",
    "lastChecked": "2026-02-28T22:29:47.974Z",
    "entryCount": 4
  },
  "tedthepraimortis": {
    "hash": "ebc01d44f9a34eb5",
    "lastChecked": "2026-02-28T22:29:47.956Z",
    "entryCount": 24
  },
  "seanwee": {
    "hash": "c4ee8bdacfbdc183",
    "lastChecked": "2026-02-28T22:29:48.095Z",
    "entryCount": 37
  },
  "tgx78": {
    "hash": "79ff2f2f245f2104",
    "lastChecked": "2026-02-28T22:29:48.046Z",
    "entryCount": 140
  },
  "smirk": {
    "hash": "4286ae57d2c63a96",
    "lastChecked": "2026-02-28T22:29:48.065Z",
    "entryCount": 65
  },
  "recode": {
    "hash": "d3feac59bc545534",
    "lastChecked": "2026-02-28T22:29:48.004Z",
    "entryCount": 143
  },
  "lown-fi": {
    "hash": "cf50ead3c74e50ef",
    "lastChecked": "2026-02-28T22:29:48.113Z",
    "entryCount": 132
  },
  "practiphile": {
    "hash": "274b6ce471c18c55",
    "lastChecked": "2026-02-28T22:29:48.147Z",
    "entryCount": 236
  },
  "mmagtech": {
    "hash": "d4a8599d592b5bbf",
    "lastChecked": "2026-02-28T22:29:48.101Z",
    "entryCount": 276
  },
  "vsg": {
    "hash": "cfdf8cd76e395110",
    "lastChecked": "2026-02-28T22:29:48.129Z",
    "entryCount": 208
  },
  "regancipher": {
    "hash": "5cdb6066d3e3ca69",
    "lastChecked": "2026-02-28T22:29:48.001Z",
    "entryCount": 138
  },
  "musicafe": {
    "hash": "96824c82786245ac",
    "lastChecked": "2026-02-28T22:29:48.128Z",
    "entryCount": 295
  },
  "treblewellxtended": {
    "hash": "c6bdb7b5e6237b0b",
    "lastChecked": "2026-02-28T22:29:48.197Z",
    "entryCount": 243
  },
  "soundignity": {
    "hash": "2c852c86eb549375",
    "lastChecked": "2026-02-28T22:29:48.294Z",
    "entryCount": 403
  },
  "therollo9": {
    "hash": "2a2d4ae820b7f233",
    "lastChecked": "2026-02-28T22:29:48.265Z",
    "entryCount": 214
  },
  "sl0the": {
    "hash": "85ad91a8e291abd9",
    "lastChecked": "2026-02-28T22:29:48.216Z",
    "entryCount": 180
  },
  "soundcheck39": {
    "hash": "db415b44c5cd7e53",
    "lastChecked": "2026-02-28T22:29:48.408Z",
    "entryCount": 430
  },
  "listener": {
    "hash": "fe3a11d981f0de61",
    "lastChecked": "2026-02-28T22:29:47.969Z",
    "entryCount": 73
  },
  "silicagel": {
    "hash": "825e2447df2f6f30",
    "lastChecked": "2026-02-28T22:29:48.231Z",
    "entryCount": 158
  },
  "auricularesargentina": {
    "hash": "3325b56cb50d10f3",
    "lastChecked": "2026-02-28T22:29:49.047Z",
    "entryCount": 87
  },
  "capraaudio": {
    "hash": "cb5a2dd9e70793e7",
    "lastChecked": "2026-02-28T22:29:49.046Z",
    "entryCount": 14
  },
  "kuulokenurkka": {
    "hash": "9d515d0ee6c433a0",
    "lastChecked": "2026-02-28T22:29:49.167Z",
    "entryCount": 159
  },
  "yoshiultra": {
    "hash": "1e38f7105c903bf8",
    "lastChecked": "2026-02-28T22:29:49.290Z",
    "entryCount": 95
  },
  "elrics": {
    "hash": "7dbea47a13202303",
    "lastChecked": "2026-02-28T22:29:49.186Z",
    "entryCount": 87
  },
  "earphonesarchive": {
    "hash": "9b347860bdc0c22d",
    "lastChecked": "2026-02-28T22:29:49.422Z",
    "entryCount": 385
  },
  "earphonesarchiveHP": {
    "hash": "89d516b0d8aa8491",
    "lastChecked": "2026-02-28T22:29:49.459Z",
    "entryCount": 203
  },
  "cammyfi": {
    "hash": "4c79736bbd71dec4",
    "lastChecked": "2026-02-28T22:29:49.355Z",
    "entryCount": 87
  },
  "sai": {
    "hash": "e197fc36e2865b33",
    "lastChecked": "2026-02-28T22:29:49.315Z",
    "entryCount": 296
  },
  "listener5128": {
    "hash": "a81af033090a1519",
    "lastChecked": "2026-02-28T22:29:48.599Z",
    "entryCount": 66
  },
  "filk": {
    "hash": "b5a096f087bb8521",
    "lastChecked": "2026-02-28T22:29:49.202Z",
    "entryCount": 101
  }
}